g_buffer_tools
