Metadata-Version: 2.1
Name: g-buffer-tools
Version: 0.0.2
Summary: a set of tools used to handle G-buffer
Home-page: https://github.com/bhiaibogf/image-process
Author: bhiaibogf
Author-email: bhiaibogf@outlook.com
License: MIT Licence
Keywords: G-buffer,image process
Platform: any
